{
  "configVersion": 1,
  "timestamp": 1757165654100,
  "index": "https://marquesCleiton.github.io/Vafyndell/index.html",
  "assetGroups": [
    {
      "name": "app",
      "installMode": "prefetch",
      "updateMode": "prefetch",
      "cacheQueryOptions": {
        "ignoreVary": true
      },
      "urls": [
        "https://marquesCleiton.github.io/Vafyndell/chunk-6MA5ICAN.js",
        "https://marquesCleiton.github.io/Vafyndell/chunk-G77W2IJD.js",
        "https://marquesCleiton.github.io/Vafyndell/chunk-QIREL3HZ.js",
        "https://marquesCleiton.github.io/Vafyndell/favicon.ico",
        "https://marquesCleiton.github.io/Vafyndell/index.html",
        "https://marquesCleiton.github.io/Vafyndell/main-K6UMBX73.js",
        "https://marquesCleiton.github.io/Vafyndell/manifest.webmanifest",
        "https://marquesCleiton.github.io/Vafyndell/polyfills-5CFQRCPP.js",
        "https://marquesCleiton.github.io/Vafyndell/styles-5INURTSO.css"
      ],
      "patterns": []
    },
    {
      "name": "assets",
      "installMode": "lazy",
      "updateMode": "prefetch",
      "cacheQueryOptions": {
        "ignoreVary": true
      },
      "urls": [
        "https://marquesCleiton.github.io/Vafyndell/icons/icon-128x128.png",
        "https://marquesCleiton.github.io/Vafyndell/icons/icon-144x144.png",
        "https://marquesCleiton.github.io/Vafyndell/icons/icon-152x152.png",
        "https://marquesCleiton.github.io/Vafyndell/icons/icon-192x192.png",
        "https://marquesCleiton.github.io/Vafyndell/icons/icon-384x384.png",
        "https://marquesCleiton.github.io/Vafyndell/icons/icon-512x512.png",
        "https://marquesCleiton.github.io/Vafyndell/icons/icon-72x72.png",
        "https://marquesCleiton.github.io/Vafyndell/icons/icon-96x96.png"
      ],
      "patterns": []
    }
  ],
  "dataGroups": [],
  "hashTable": {
    "https://marquesCleiton.github.io/Vafyndell/chunk-6MA5ICAN.js": "3e5e73c04aeb913351c9dcf425ac45cf1bf44dcf",
    "https://marquesCleiton.github.io/Vafyndell/chunk-G77W2IJD.js": "50a9c8e7968651481f81e1277648913305b30447",
    "https://marquesCleiton.github.io/Vafyndell/chunk-QIREL3HZ.js": "cc62b88e29d384ab221cae564b34b7c30224545c",
    "https://marquesCleiton.github.io/Vafyndell/favicon.ico": "9c39f434fe1261f68c5e3eefdf734630d99c5670",
    "https://marquesCleiton.github.io/Vafyndell/icons/icon-128x128.png": "f912963bdc6d5a38d8f1dd0afbaab2ce8d657acb",
    "https://marquesCleiton.github.io/Vafyndell/icons/icon-144x144.png": "b155fd5f2fd5d2ea7760721063003c4cd95fd783",
    "https://marquesCleiton.github.io/Vafyndell/icons/icon-152x152.png": "eae6e0f0c8afb8aaae339e2a569b43e9238e5e6c",
    "https://marquesCleiton.github.io/Vafyndell/icons/icon-192x192.png": "15c4180454633880d98674aa7394656196c91584",
    "https://marquesCleiton.github.io/Vafyndell/icons/icon-384x384.png": "94a915751ef6c9282df9aea405ad679230631814",
    "https://marquesCleiton.github.io/Vafyndell/icons/icon-512x512.png": "1de182f76f7329dfa8f9fcdd1fdcdd695bea6a99",
    "https://marquesCleiton.github.io/Vafyndell/icons/icon-72x72.png": "aa88a6096bd973be7f6d7a5489bfa6bc2463f8c4",
    "https://marquesCleiton.github.io/Vafyndell/icons/icon-96x96.png": "7fb8f59c30ce2ff12c700321a0b39e14b3dc8f95",
    "https://marquesCleiton.github.io/Vafyndell/index.html": "289aab423da1c12796c8b8d18947df4b9ba3c005",
    "https://marquesCleiton.github.io/Vafyndell/main-K6UMBX73.js": "c393c85bbe720d58fca045e78f1c5f4a7d09f646",
    "https://marquesCleiton.github.io/Vafyndell/manifest.webmanifest": "12d3e5aa920329e44fb74a37855cd18d7aaa7901",
    "https://marquesCleiton.github.io/Vafyndell/polyfills-5CFQRCPP.js": "f2241e9a25858f895ce299d15f6f22e849e2fd72",
    "https://marquesCleiton.github.io/Vafyndell/styles-5INURTSO.css": "da39a3ee5e6b4b0d3255bfef95601890afd80709"
  },
  "navigationUrls": [
    {
      "positive": true,
      "regex": "^\\/.*$"
    },
    {
      "positive": false,
      "regex": "^\\/(?:.+\\/)?[^/]*\\.[^/]*$"
    },
    {
      "positive": false,
      "regex": "^\\/(?:.+\\/)?[^/]*__[^/]*$"
    },
    {
      "positive": false,
      "regex": "^\\/(?:.+\\/)?[^/]*__[^/]*\\/.*$"
    }
  ],
  "navigationRequestStrategy": "performance"
}